SimpleRequests.py
setup.py
SimpleRequests.egg-info/PKG-INFO
SimpleRequests.egg-info/SOURCES.txt
SimpleRequests.egg-info/dependency_links.txt
SimpleRequests.egg-info/top_level.txt