Metadata-Version: 1.1
Name: SimpleRequests
Version: 0.2
Summary: request url for json type
Home-page: https://github.com/saintic/SimpleRequests
Author: Mr.tao
Author-email: staugur@saintic.com
License: MIT
Download-URL: https://github.com/saintic/SimpleRequests/releases/tag/v0.2
Keywords: requests,url,RESTful API
Platform: UNKNOWN
Classifier: Environment :: Other Environment
Classifier: Intended Audience :: Developers
Classifier: License :: OSI Approved :: MIT License
Classifier: Operating System :: POSIX :: Linux
Classifier: Programming Language :: Python
Classifier: Topic :: Internet
Classifier: Topic :: Software Development :: Libraries :: Python Modules
